images2video
build
