Metadata-Version: 1.1
Name: images2video
Version: 0.3
Summary: Python images to video library using OpenCV
Home-page: https://github.com/messense/images2video
Author: messense
Author-email: messense@icloud.com
License: UNKNOWN
Keywords: opencv,video
Platform: UNKNOWN
Classifier: Development Status :: 4 - Beta
Classifier: License :: OSI Approved :: MIT License
Classifier: Operating System :: MacOS
Classifier: Operating System :: POSIX
Classifier: Operating System :: POSIX :: Linux
Classifier: Programming Language :: Python
Classifier: Programming Language :: Python :: 2.7
